mdpolars/__init__.py
mdpolars/utils.py
mdpolars/version.py
mdpolars-0.1.0.dist-info/LICENSE
mdpolars-0.1.0.dist-info/METADATA
mdpolars-0.1.0.dist-info/WHEEL
mdpolars-0.1.0.dist-info/RECORD
