Metadata-Version: 2.1
Name: mdpolars
Version: 0.1.0
Summary: a simpler tool for convert markdown table to polars
Home-page: https://github.com/kyoto7250/mdpolars_py
License: MIT
Keywords: polars,markdown,table,test,development
Author: kyoto7250
Author-email: 50972773+kyoto7250@users.noreply.github.com
Requires-Python: >=3.9,<4.0
Classifier: License :: OSI Approved :: MIT License
Classifier: Programming Language :: Python :: 3
Classifier: Programming Language :: Python :: 3.9
Classifier: Programming Language :: Python :: 3.10
Classifier: Programming Language :: Python :: 3.11
Requires-Dist: polars (>=0.19.8,<0.20.0)
Project-URL: Repository, https://github.com/kyoto7250/mdpolars_py
